cute_shm/__init__.py
cute_shm/core.py
cute_shm/evaluation.py
cute_shm/hdf5_shm.py
cute_shm/main.py
cute_shm/numpy_shm.py
cute_shm/progress.py
cute_shm-1.2.dist-info/LICENSE
cute_shm-1.2.dist-info/METADATA
cute_shm-1.2.dist-info/WHEEL
cute_shm-1.2.dist-info/entry_points.txt
cute_shm-1.2.dist-info/RECORD
