Metadata-Version: 2.1
Name: cute-shm
Version: 1.2
Summary: managing np arrays stored in the shared memory
Home-page: https://github.com/MPI-IS/cute-shm
Author: Vincent Berenz
Author-email: vberenz@tuebingen.mpg.de
Requires-Python: >=3.10,<4.0
Classifier: Programming Language :: Python :: 3
Classifier: Programming Language :: Python :: 3.10
Classifier: Programming Language :: Python :: 3.11
Classifier: Programming Language :: Python :: 3.12
Requires-Dist: filelock (>=3.15.4,<4.0.0)
Requires-Dist: h5py (>=3.11.0,<4.0.0)
Requires-Dist: numpy (>=2.0.1,<3.0.0)
Requires-Dist: psutil (>=6.0.0,<7.0.0)
Requires-Dist: rich (>=13.7.1,<14.0.0)
Requires-Dist: tomli (>=2.0.1,<3.0.0)
Requires-Dist: tomli-w (>=1.0.0,<2.0.0)
Project-URL: Repository, https://github.com/MPI-IS/cute-shm
